aphie/__init__.py
aphie/main.py
aphie/py.typed
aphie-0.0.3.dist-info/licenses/LICENSE
aphie-0.0.3.dist-info/METADATA
aphie-0.0.3.dist-info/WHEEL
aphie-0.0.3.dist-info/top_level.txt
aphie-0.0.3.dist-info/RECORD
