Metadata-Version: 2.4
Name: aphie
Version: 0.0.3
Summary: Pydantic to argparse
Author-email: me@wvlab.xyz
Maintainer-email: wvlab <me@wvlab.xyz>
License-Expression: MIT
Project-URL: Repository, https://github.com/wvlab/aphie
Project-URL: Issues, https://github.com/wvlab/aphie/issues
Project-URL: Changelog, https://github.com/me/spam/blob/master/CHANGELOG.md
Classifier: Development Status :: 1 - Planning
Classifier: Framework :: Pydantic
Classifier: Intended Audience :: Developers
Classifier: Programming Language :: Python
Classifier: Typing :: Typed
Requires-Python: >=3.12
License-File: LICENSE
Requires-Dist: pydantic>=2.11
Dynamic: license-file
